hbdl/__init__.py
hbdl/__main__.py
hbdl/hbdl.py
hbdl-0.0.6.dist-info/LICENSE
hbdl-0.0.6.dist-info/METADATA
hbdl-0.0.6.dist-info/WHEEL
hbdl-0.0.6.dist-info/entry_points.txt
hbdl-0.0.6.dist-info/top_level.txt
hbdl-0.0.6.dist-info/RECORD
