Metadata-Version: 2.1
Name: hbdl
Version: 0.0.6
Summary: Another humble bundle downloader
Home-page: https://github.com/unkloud/hbdl.git
Author: unkloud
Author-email: unkloud.com.au@gmail.com
License: UNKNOWN
Platform: UNKNOWN
Classifier: Programming Language :: Python :: 3
Classifier: Programming Language :: Python :: 3.7
Classifier: Programming Language :: Python :: 3.8
Classifier: Programming Language :: Python :: 3.9
Classifier: License :: OSI Approved :: MIT License
Classifier: Operating System :: OS Independent
Requires-Dist: Click (==8.0.1)
Requires-Dist: requests (==2.26.0)
